{
    "last_update": "2026-07-03 02:21:44",
    "total_products": 2,
    "products": [
        {
            "id": 1,
            "name": "Panadol Extra 500mg",
            "meta": "Caja 16 tabletas · Paracetamol + Cafeína",
            "image": "https://images.unsplash.com/photo-1584308666744-24d5c474f2ae?w=300",
            "category": "Analgésicos",
            "prices": [
                {
                    "pharmacy": "Fischel",
                    "price": 3250,
                    "link": "https://fischelenlinea.com/search?q=panadol",
                    "stock": "Disponible"
                },
                {
                    "pharmacy": "FarmaValue",
                    "price": 2850,
                    "link": "https://farmavalue.com/cr/",
                    "stock": "Disponible"
                },
                {
                    "pharmacy": "La Bomba",
                    "price": 2900,
                    "link": "https://farmacialabomba.com/",
                    "stock": "Oferta"
                },
                {
                    "pharmacy": "Sucre",
                    "price": 3150,
                    "link": "https://sucreenlinea.com/",
                    "stock": "Disponible"
                }
            ]
        },
        {
            "id": 2,
            "name": "Ozempic 1mg",
            "meta": "Solución inyectable · Control Glucémico",
            "image": "https://images.unsplash.com/photo-1584308666744-24d5c474f2ae?w=300",
            "category": "Diabetes",
            "prices": [
                {
                    "pharmacy": "Fischel",
                    "price": 72000,
                    "link": "https://fischelenlinea.com",
                    "stock": "Disponible"
                },
                {
                    "pharmacy": "FarmaValue",
                    "price": 62450,
                    "link": "https://farmavalue.com/cr",
                    "stock": "Oferta"
                },
                {
                    "pharmacy": "La Bomba",
                    "price": 63000,
                    "link": "https://farmacialabomba.com",
                    "stock": "Disponible"
                },
                {
                    "pharmacy": "Sucre",
                    "price": 69500,
                    "link": "https://sucreenlinea.com",
                    "stock": "Disponible"
                }
            ]
        }
    ]
}